Workbook

Sheet Custos gerais
B3: Item | C3: Custo Total | D3: Custo Franquia (Por cliente) | E3: Franquia
B4: Custos médios administrativos da empresa (Anual) | C4: 24000 | D4: =C4/E4 -> 80 | E4: 300
B5: Taxa média de checkout Cartão (Crédito e Débito) - sob valor do serviço | C5: 0.05 | D5: não se aplica
B6: Taxa média de checkout Pix - sob valor do serviço | C6: 0.0099 | D6: não se aplica
B7: Impostos sobre valor total de serviço - após inclusão de taxas de checkout | C7: 0.08 | D7: não se aplica

Sheet BPlen HUB Custos
B2: Histórico: Mar26 a Jun26
B3: Item / Serviço | C3: Custo Total Período | D3: Base de Cálculo / Detalhamento
B4: Honorário Dev (Histórico) | C4: 184800 | D4: R$ Hora: 350,00 | Horas dedicadas (Mar-26 a Jun-26): 528h
B5: Google Workspace (Setup) | C5: 567.2 | D5: Proporcional a 4 meses de uso de homologação
B6: Google Cloud (Setup/Testes) | C6: 0 | D6: Consumido 100% dentro do bônus promocional de R$ 1.700,00
B7: TOTAL INVESTIDO | C7: 21567.2 | D7: Investimento total para colocar a plataforma em produção
B10: Projeção: Próx 12 meses
B11: Item / Serviço | C11: Custo Mensal (Proj.) | D11: Custo Anual (Proj.) | E11: Detalhamento / Objetivo
B12: Google Workspace | C12: 141.8 | D12: 1701.6 | E12: E-mails, Drive e agenda corporativos
B13: Vercel Pro | C13: 90 | D13: 1080 | E13: Servidor do site com suporte a IA
B14: Notion Business | C14: 90 | D14: 1080 | E14: Banco de dados de tarefas e rotinas
B15: Resend Pro (E-mails) | C15: 90 | D15: 1080 | E15: Disparo de e-mails automáticos (Novo)
B16: Google Cloud (GCP/IA) | C16: 100 | D16: 1200 | E16: Banco Firestore + Tokens de IA (Gemini)
B17: Domínio (.com.br) | C17: 3.33 | D17: 40 | E17: Registro anual no Registro.br (Novo)
B18: Cloudflare | C18: 0 | D18: 0 | E18: Segurança e proteção DDoS (Grátis)
B19: Mercado Pago Gateway | C19: 0 | D19: 0 | E19: Taxa variável de 3.99% a 4.99% por venda
B20: Dev On-Demand | C20: 7000 | D20: =C20*12 -> 84000
B21: TOTAL PROJETADO | C21: =SUM(C12:C20) -> 7515.13 | D21: =SUM(D12:D20) -> 90181.6
B25: INVESTIDO + PROJETADO | C25: =SUM(C7+C21) -> 29082.33

Sheet MentoCoach Custos
B4: Metodologia Coach IBC (Investimento)
B5: 6000

Sheet Referencias de Custos
A1: Item | B1: Minutos Totais | C1: Custo | D1: Custo por Minuto | E1: Descrição
A2: Honorário | B2: 60 | C2: 350 | D2: =C2/B2 -> 5.8333333 | E2: Tempo dedicado dos consultores
A4: Item | B4: Acessos Totais | C4: Custo | D4: Custo por Acesso | E4: Descrição
A5: Área Membro | B5: 1 | C5: 15 | D5: =C5/B5 -> 15 | E5: Acesso ao dashboard de assessments + agenda bplen + acompanhamento de jornada
A6: Área Membro | GDC Dashboard | B6: 1 | C6: 15 | D6: =C6/B6 -> 15 | E6: Acesso ao modulo de gestão e desenvolvimento de carreira com recursos de acompanhamento detalhado de métricas e documentação de progresso + gestão de onbjetivos e metas + backlog list
A8: Item | B8: Sistema Total | C8: Custo | D8: Custo por Sistema | E8: Descrição
A9: BPlen HUB | B9: 1 | C9: 29082.33 | D9: =C9/B9 -> 29082.33 | E9: Ecossistema BPlen HUB | Area logada que oferece diversos recursos para consumo dos serviços Bplen e tornar a experiencia do cliente mais fluida e confiável aliado a tecnologia.
A10: MentoCoach | B10: 1 | C10: 6000 | D10: =C10/B10 -> 6000 | E10: Ferramentas e Métodologia de Coching e Mentoria | Acesso ao modulo de assessments, exercícios e tarefas especificos para coaching e mentoria
A12: Item | B12: Relatórios Totais | C12: Custo | D12: Custo por Relatório | E12: Descrição
A13: Relatório DISC | B13: 1 | C13: 160 | D13: =C13/B13 -> 160 | E13: Relatório com resultados da avaliação DISC
A14: Relatório de Análise Comportamental | B14: 1 | C14: 160 | D14: =C14/B14 -> 160 | E14: Relatório da análise e insights do analista referente aos assessments comportamentais cruzados com contexto situacionais do cliente.
A15: Relatório PDI | B15: 1 | C15: 150 | D15: =C15/B15 -> 150 | E15: Relatório da análise e insights do analista referente ao plano de carreira cruzado com assessments comportamentais e contexto situacionais do cliente.
A17: Item | B17: Kits Totais | C17: Custo | D17: Custo por Kit | E17: Descrição
A18: KIT BPlen | B18: 1 | C18: 150 | D18: =C18/B18 -> 150 | E18: Itens personalizados da Bplen (Caderno, Caneta e outros necessários para complemento prático de atividades e tarefas dos clientes)
A20: Item | B20: Taxa | C20: - | D20: - | E20: Descrição
A21: Taxa Checkout | B21: 0.05 | C21: não se aplica | D21: não se aplica | E21: Taxa de pagamento com cartão de debito ou crédito
A22: Taxa Imposto | B22: 0.08 | C22: não se aplica | D22: não se aplica | E22: Taxa de impostos sob custo bruto do serviço
A24: Item | B24: e-book Totais | C24: Custo | D24: Custo por e-book | E24: Descrição
A25: GDC e-book | B25: 1 | C25: 5000 | D25: =C25/B25 -> 5000 | E25: Material pedagógico para condução de orientação educacional sobre Gestão e Desenvolvimento de Carreira.
A26: Posicionamento de Carreira e-book | B26: 1 | C26: 5000 | D26: =C26/B26 -> 5000 | E26: Material pedagógico para condução de orientação educacional sobre Posicionamento de Carreira.
A28: Item | B28: franquia Totais | C28: Custo | D28: Custo por e-book | E28: Descrição
A29: GDC e-book - franquia | B29: 25 | C29: 5000 | D29: =C29/B29 -> 200 | E29: Disponibilização do item ou serviço dividindo seu custo total por "franquias" (número de clientes)
A30: Honorário - Franquia | B30: 10 | C30: =C2 -> 350 | D30: =C30/B30 -> 35 | E30: Disponibilização do item ou serviço dividindo seu custo total por "franquias" (número de clientes)
A31: Posicionamento de Carreira e-book - franquia | B31: 100 | C31: =C26 -> 5000 | D31: =C31/B31 -> 50 | E31: Disponibilização do item ou serviço dividindo seu custo total por "franquias" (número de clientes)
A32: BPlen HUB - franquia | B32: 1000 | C32: =C9 -> 29082.33 | D32: =C32/B32 -> 29.08233 | E32: Disponibilização do item ou serviço dividindo seu custo total por "franquias" (número de clientes)
A33: Área Membro | MentoCoach Dashboard - franquia | B33: 20 | C33: =C10 -> 6000 | D33: =C33/B33 -> 300 | E33: Disponibilização do item ou serviço dividindo seu custo total por "franquias" (número de clientes)
A34: Custos Administrativos - franquia | B34: 300 | C34: ='Custos gerais'!C4 -> 24000 | D34: =C34/B34 -> 80 | E34: Disponibilização do item ou serviço dividindo seu custo total por "franquias" (número de clientes)

Sheet Custo de Serviços
C1: Margem: | D1: 0.2
C3: 1 to 1
C4: Item | D4: Unidade | E4: Custo | F4: Obs
C5: Custos Administrativos - franquia | D5: 1 | E5: 80
C6: Honorário | D6: 45 | E6: =D6*'Referencias de Custos'!$D$2 -> 262.5
C7: Subtotal bruto | D7: - | E7: =SUM(E5:E6) -> 342.5
C8: Margem | D8: - | E8: =E7*$D$1 -> 68.5
C9: Sub + Margem | D9: - | E9: =E8+E7 -> 411
C11: Cenário checkout cartão (a)
C12: Taxa Checkout | D12: 0.05 | E12: =E9*D12 -> 20.55
C13: Taxa Imposto | D13: 0.08 | E13: =(E12+E9)*D13 -> 34.524
C14: Total Líquido (a) | D14: - | E14: =SUM(E12:E13,E9) -> 466.074
C15: Desconto Máximo (a) | D15: 0.03 | E15: =-E14*D15 -> -13.98222
C16: Parcelamento Máximo | D16: 0
C18: Cenário checkout PIX (b)
C19: Taxa Checkout | D19: 0.01 | E19: =E9*D19 -> 4.11
C20: Taxa Imposto | D20: 0.08 | E20: =(E19+E9)*D20 -> 33.2088
C21: Total Líquido (b) | D21: - | E21: =SUM(E19:E20,$E$9) -> 448.3188
C22: Desconto Máximo (b) | D22: 0 | E22: =-E21*D22 -> 0
C24: Desconto Membro Bplen | D24: =E24/E21 -> -0.17844445 | E24: =-(E5) -> -80
C26: Publicidade na Página de serviços? | D26: Não
C28: Posicionamento de Carreira
C29: Item | D29: Unidade | E29: Custo | F29: Obs
C30: Custos Administrativos - franquia | D30: 1 | E30: 80
C31: BPlen HUB - franquia | D31: 1 | E31: 29.08
C32: Posicionamento de Carreira e-book - franquia | D32: 1 | E32: ='Referencias de Custos'!D31 -> 50
C33: Honorário | D33: 90 | E33: =D33*'Referencias de Custos'!$D$2 -> 525 | F33: 1 to 1 (30min), Devolutiva (60min)
C34: Subtotal bruto | D34: - | E34: =SUM(E30:E33) -> 684.08
C35: Margem | D35: - | E35: =E34*$D$1 -> 136.816
C36: Sub + Margem | D36: - | E36: =E35+E34 -> 820.896
C38: Cenário checkout cartão (a)
C39: Taxa Checkout | D39: 0.05 | E39: =E36*D39 -> 41.0448
C40: Taxa Imposto | D40: 0.08 | E40: =(E39+E36)*D40 -> 68.955264
C41: Total Líquido (a) | D41: - | E41: 930.9
C42: Desconto Máximo (a) | D42: 0.03 | E42: =-E41*D42 -> -27.927
C43: Parcelamento Máximo | D43: 3 | E43: =E41/D43 -> 310.3
C45: Cenário checkout PIX (b)
C46: Taxa Checkout | D46: 0.01 | E46: =E36*D46 -> 8.20896
C47: Taxa Imposto | D47: 0.08 | E47: =(E46+E36)*D47 -> 66.328397
C48: Total Líquido (b) | D48: - | E48: 895.43
C49: Desconto Máximo (b) | D49: 0 | E49: =-E48*D49 -> 0
C51: Desconto Membro Bplen | D51: =E51/E48 -> -0.12181857 | E51: =-(E30+E31) -> -109.08
C54: Publicidade na Página de serviços? | D54: Sim
C56: Análise Comportamental
C57: Item | D57: Unidade | E57: Custo | F57: Obs
C58: Custos Administrativos - franquia | D58: 1 | E58: 80
C59: BPlen HUB - franquia | D59: 1 | E59: 29.08
C60: Área Membro | D60: 1 | E60: 15
C61: Relatório DISC | D61: 1 | E61: 160
C62: Relatório de Análise Comportamental | D62: 1 | E62: 160
C63: Honorário | D63: 120 | E63: =D63*'Referencias de Custos'!$D$2 -> 700 | F63: Análise Comportamental (60min), Devolutiva Comportamental (60min)
C64: Honorário - Franquia | D64: 2 | E64: =D64*'Referencias de Custos'!$D$30 -> 70 | F64: Onboarding (60min), Offboarding (60min)
C65: Subtotal bruto | D65: - | E65: =SUM(E58:E64) -> 1214.08
C66: Margem | D66: - | E66: =E65*$D$1 -> 242.816
C67: Sub + Margem | D67: - | E67: =E66+E65 -> 1456.896
C69: Cenário checkout cartão (a)
C70: Taxa Checkout | D70: 0.05 | E70: =E67*D70 -> 72.8448
C71: Taxa Imposto | D71: 0.08 | E71: =(E70+E67)*D71 -> 122.37926
C72: Total Líquido (a) | D72: - | E72: 1652.12
C73: Desconto Máximo (a) | D73: 0.03 | E73: =-E72*D73 -> -49.5636
C74: Parcelamento Máximo | D74: 5 | E74: =E72/D74 -> 330.424
C76: Cenário checkout PIX (b)
C77: Taxa Checkout | D77: 0.01 | E77: =E67*D77 -> 14.56896
C78: Taxa Imposto | D78: 0.08 | E78: =(E77+E67)*D78 -> 117.7172
C79: Total Líquido (b) | D79: - | E79: 1589.18
C80: Desconto Máximo (b) | D80: 0 | E80: =-E79*D80 -> 0
C82: Desconto Membro Bplen | D82: =E82/E79 -> -0.29831737 | E82: =-(E58+E59+E60+350) -> -474.08
C84: Publicidade na Página de serviços? | D84: Sim
C86: Plano de Carreira
C87: Item | D87: Unidade | E87: Custo | F87: Obs
C88: Custos Administrativos - franquia | D88: 1 | E88: 80
C89: BPlen HUB - franquia | D89: 1 | E89: 29.08
C90: Área Membro | D90: 1 | E90: 15
C91: Relatório PDI | D91: 1 | E91: 160
C92: Honorário | D92: 180 | E92: =D92*'Referencias de Custos'!$D$2 -> 1050 | F92: Análise de Plano de Carreira (60min), Devolutiva de Plano de Carreira (60min), Avaliação de Elegibilidade para Plano de Carreira (60min)
C93: Honorário - Franquia | D93: 2 | E93: =D93*'Referencias de Custos'!$D$30 -> 70 | F93: Onboarding (60min), Offboarding (60min)
C95: Subtotal bruto | D95: - | E95: =SUM(E88:E93) -> 1404.08
C96: Margem | D96: - | E96: =E95*$D$1 -> 280.816
C97: Sub + Margem | D97: - | E97: =E96+E95 -> 1684.896
C99: Cenário checkout cartão (a)
C100: Taxa Checkout | D100: 0.05 | E100: =E97*D100 -> 84.2448
C101: Taxa Imposto | D101: 0.08 | E101: =(E100+E97)*D101 -> 141.53126
C102: Total Líquido (a) | D102: - | E102: 1910.67
C103: Desconto Máximo (a) | D103: 0.03 | E103: =-E102*D103 -> -57.3201
C104: Parcelamento Máximo | D104: 5 | E104: =E102/D104 -> 382.134
C106: Cenário checkout PIX (b)
C107: Taxa Checkout | D107: 0.01 | E107: =E97*D107 -> 16.84896
C108: Taxa Imposto | D108: 0.08 | E108: =(E107+E97)*D108 -> 136.1396
C109: Total Líquido (b) | D109: - | E109: 1837.88
C110: Desconto Máximo (b) | D110: 0 | E110: =-E109*D110 -> 0
C112: Desconto Membro Bplen | D112: =E112/E109 -> -0.25794938 | E112: =-(E88+E89+E90+350) -> -474.08 | F112: Desconto condicionado a conclusão da etapa Análise Comportamental
C114: Publicidade na Página de serviços? | D114: Sim
C115: Obs: | D115: O serviço apenas poderá ser obtido por clientes que já concluíram a etapa de análise comportamental da Bplen ou aprovados no processo de Avaliação de Elegibilidade
C117: Gestão e Desenvolvimento de Carreira
C118: Item | D118: Unidade | E118: Custo | F118: Obs
C119: Custos Administrativos - franquia | D119: 1 | E119: 80
C120: BPlen HUB - franquia | D120: 1 | E120: 29.08
C121: Área Membro | D121: 1 | E121: 15
C122: Área Membro | GDC Dashboard | D122: 1 | E122: 15
C123: GDC e-book - franquia | D123: 1 | E123: ='Referencias de Custos'!D29 -> 200
...

Sheet Pacotes de Serviço
D2: BPlen HUB
D3: Precificação de Pacotes Estruturados (Deduplicação de Custos & Impostos Simplificados)
B6: 1. Resumo Comercial dos Pacotes de Serviço
B7: Pacote | C7: Composição de Serviços | D7: Subtotal Bruto | E7: Margem (20%) | F7: Preço Cartão | G7: Preço PIX (Sugerido) | H7: Soma Individual (Cartão) | I7: Soma Individual (PIX) | J7: Economia p/ Cliente (PIX)
B8: Junior | C8: Posicionamento de Carreira | D8: =E22 -> 684.08233 | E8: =E23 -> 136.81647 | F8: 930.9 | G8: 895.44 | H8: ='Custo de Serviços'!$E$41 -> 930.9 | I8: ='Custo de Serviços'!$E$48 -> 895.43 | J8: =I8-G8 -> -0.01
B9: Pleno | C9: Junior + Análise Comportamental | D9: =E43 -> 1789.0823 | E9: =E44 -> 357.81647 | F9: 2434.58 | G9: 2341.84 | H9: ='Custo de Serviços'!$E$41 + 'Custo de Serviços'!$E$72 -> 2583.02 | I9: ='Custo de Serviços'!$E$48 + 'Custo de Serviços'!$E$79 -> 2484.61 | J9: =I9-G9 -> 142.77
B10: Senior | C10: Pleno + Plano de Carreira | D10: =E66 -> 2999.0823 | E10: =E67 -> 599.81647 | F10: 4081.15 | G10: 3925.68 | H10: ='Custo de Serviços'!$E$41 + 'Custo de Serviços'!$E$72 + 'Custo de Serviços'!$E$102 -> 4493.69 | I10: ='Custo de Serviços'!$E$48 + 'Custo de Serviços'!$E$79 + 'Custo de Serviços'!$E$109 -> 4322.49 | J10: =I10-G10 -> 396.81
B11: Lider | C11: Senior + Gestão e Desenvolvimento (GDC) | D11: =E91 -> 11264.082 | E11: =E92 -> 2252.8165 | F11: 15328.16 | G11: 14744.23 | H11: ='Custo de Serviços'!$E$41 + 'Custo de Serviços'!$E$72 + 'Custo de Serviços'!$E$102 + 'Custo de Serviços'!$E$133 -> 16004.81 | I11: ='Custo de Serviços'!$E$48 + 'Custo de Serviços'!$E$79 + 'Custo de Serviços'!$E$109 + 'Custo de Serviços'!$E$140 -> 15395.09 | J11: =I11-G11 -> 650.86
B12: Embaixador BPlen | C12: Lider | D12: =E116 -> 17464.082 | E12: =E117 -> 3492.8165 | F12: 23765.12 | G12: 22859.79 | H12: ='Custo de Serviços'!$E$41 + 'Custo de Serviços'!$E$72 + 'Custo de Serviços'!$E$102 + 'Custo de Serviços'!$E$133 + 'Custo de Serviços'!$E$162 -> 24828.35 | I12: ='Custo de Serviços'!$E$48 + 'Custo de Serviços'!$E$79 + 'Custo de Serviços'!$E$109 + 'Custo de Serviços'!$E$140 + 'Custo de Serviços'!$E$169 -> 23882.49 | J12: =I12-G12 -> 1022.7
B14: 2. Detalhamento de Custos e Lógica de Formação de Preço por Pacote
B16: Pacote JUNIOR
B17: Item de Custo | C17: Unidade | D17: Custo Unitário | E17: Custo Consolidado | F17: Racional / Origem
B18: Custos Administrativos - franquia | C18: 1 | D18: ='Referencias de Custos'!$D$34 -> 80 | E18: =C18*D18 -> 80 | F18: Custo administrativo diluído por cliente
B19: BPlen HUB - franquia | C19: 1 | D19: ='Referencias de Custos'!$D$32 -> 29.08233 | E19: =C19*D19 -> 29.08233 | F19: Custo de desenvolvimento do portal diluído
B20: Posicionamento de Carreira e-book - franquia | C20: 1 | D20: ='Referencias de Custos'!D31 -> 50 | E20: =C20*D20 -> 50 | F20: Material pedagógico para condução de orientação educacional sobre Posicionamento de Carreira.
B21: Honorário (Sessões) | C21: 90 | D21: ='Referencias de Custos'!$D$2 -> 5.8333333 | E21: =C21*D21 -> 525 | F21: Posicionamento de Carreira: 1 to 1 (30min), Devolutiva (60min)
B22: Subtotal Bruto (Custo Base) | E22: =SUM(E18:E21) -> 684.08233
B23: Margem de Lucro BPlen (20%) | E23: =E22*'Custo de Serviços'!$D$1 -> 136.81647
B24: Subtotal + Margem | E24: =E22+E23 -> 820.8988
B25: Taxa Checkout Cartão (5% - Margem MP) | E25: =E24*'Custo de Serviços'!$D$39 -> 41.04494
B26: Impostos sobre Venda (8%) | E26: =(E24+E25)*'Custo de Serviços'!$D$40 -> 68.955499
B27: Total Consolidado (Cartão) | E27: =SUM(E24:E26) -> 930.89923
B28: Taxa Checkout PIX (1% - MP) | E28: =E24*'Custo de Serviços'!$D$46 -> 8.208988
B29: Impostos sobre Venda PIX (8%) | E29: =(E24+E28)*'Custo de Serviços'!$D$47 -> 66.328623
B30: Parcelamento Máximo | C30: 3 | D30: - | E30: -
B31: Total Consolidado (PIX) | C31: 5 | E31: =SUM(E24,E28:E29) -> 895.43641
B33: Pacote PLENO
B34: Item de Custo | C34: Unidade | D34: Custo Unitário | E34: Custo Consolidado | F34: Racional / Origem
B35: Custos Administrativos - franquia | C35: 1 | D35: ='Referencias de Custos'!$D$34 -> 80 | E35: =C35*D35 -> 80 | F35: Cobrado apenas uma vez por cliente (DEDUPLICADO)
B36: BPlen HUB - franquia | C36: 1 | D36: ='Referencias de Custos'!$D$32 -> 29.08233 | E36: =C36*D36 -> 29.08233 | F36: Cobrado apenas uma vez por cliente (DEDUPLICADO)
B37: Posicionamento de Carreira e-book - franquia | C37: 1 | D37: ='Referencias de Custos'!D31 -> 50 | E37: =C37*D37 -> 50 | F37: Material pedagógico para condução de orientação educacional sobre Posicionamento de Carreira.
B38: Área Membro | C38: 1 | D38: ='Referencias de Custos'!$D$5 -> 15 | E38: =C38*D38 -> 15 | F38: Acesso unificado à Área do Membro
B39: Relatório DISC | C39: 1 | D39: ='Referencias de Custos'!$D$13 -> 160 | E39: =C39*D39 -> 160 | F39: Relatório com resultados da avaliação DISC
B40: Relatório de Análise Comportamental | C40: 1 | D40: ='Referencias de Custos'!D14 -> 160 | E40: =C40*D40 -> 160 | F40: Relatório da análise e insights do analista referente aos assessments comportamentais cruzados com contexto situacionais do cliente.
B41: Honorário (Sessões) | C41: =90+120 -> 210 | D41: ='Referencias de Custos'!$D$2 -> 5.8333333 | E41: =C41*D41 -> 1225 | F41: PC: 90min + AC: 120min (Total: 210 minutos)
B42: Honorário - Franquia (Onboarding/Offboarding) | C42: 2 | D42: ='Referencias de Custos'!$D$30 -> 35 | E42: =C42*D42 -> 70 | F42: 1x Onboarding (35.00) + 1x Offboarding (35.00)
B43: Subtotal Bruto (Custo Base) | E43: =SUM(E35:E42) -> 1789.0823
B44: Margem de Lucro BPlen (20%) | E44: =E43*'Custo de Serviços'!$D$1 -> 357.81647
B45: Subtotal + Margem | E45: =E43+E44 -> 2146.8988
B46: Taxa Checkout Cartão (5%) | E46: =E45*'Custo de Serviços'!$D$39 -> 107.34494
B47: Impostos sobre Venda (8%) | E47: =(E45+E46)*'Custo de Serviços'!$D$40 -> 180.3395
B48: Total Consolidado (Cartão) | E48: =SUM(E45:E47) -> 2434.5832
B49: Taxa Checkout PIX (1%) | E49: =E45*'Custo de Serviços'!$D$46 -> 21.468988
B50: Impostos sobre Venda PIX (8%) | E50: =(E45+E49)*'Custo de Serviços'!$D$47 -> 173.46942
B51: Parcelamento Máximo | C51: 5 | D51: - | E51: -
B52: Total Consolidado (PIX) | E52: =SUM(E45,E49:E50) -> 2341.8372
C53: 7
B55: Pacote SENIOR
B56: Item de Custo | C56: Unidade | D56: Custo Unitário | E56: Custo Consolidado | F56: Racional / Origem
B57: Custos Administrativos - franquia | C57: 1 | D57: ='Referencias de Custos'!$D$34 -> 80 | E57: =C57*D57 -> 80 | F57: Cobrado apenas uma vez por cliente (DEDUPLICADO)
B58: BPlen HUB - franquia | C58: 1 | D58: ='Referencias de Custos'!$D$32 -> 29.08233 | E58: =C58*D58 -> 29.08233 | F58: Cobrado apenas uma vez por cliente (DEDUPLICADO)
B59: Posicionamento de Carreira e-book - franquia | C59: 1 | D59: ='Referencias de Custos'!D31 -> 50 | E59: =C59*D59 -> 50 | F59: Material pedagógico para condução de orientação educacional sobre Posicionamento de Carreira.
B60: Área Membro | C60: 1 | D60: ='Referencias de Custos'!$D$5 -> 15 | E60: =C60*D60 -> 15 | F60: Acesso unificado à Área do Membro (DEDUPLICADO)
B61: Relatório DISC | C61: 1 | D61: ='Referencias de Custos'!$D$13 -> 160 | E61: =C61*D61 -> 160 | F61: Relatório com resultados da avaliação DISC
B62: Relatório de Análise Comportamental | C62: 1 | D62: ='Referencias de Custos'!D14 -> 160 | E62: =C62*D62 -> 160 | F62: Relatório da análise e insights do analista referente aos assessments comportamentais cruzados com contexto situacionais do cliente.
B63: Relatório PDI | C63: 1 | D63: ='Custo de Serviços'!$E$91 -> 160 | E63: =C63*D63 -> 160 | F63: Relatório do Plano de Desenvolvimento Individual (PDI)
B64: Honorário (Sessões) | C64: =90+120+180 -> 390 | D64: ='Referencias de Custos'!$D$2 -> 5.8333333 | E64: =C64*D64 -> 2275 | F64: PC: 90min + AC: 120min + Plano: 180min (Total: 390 minutos)
B65: Honorário - Franquia (Onboarding/Offboarding) | C65: 2 | D65: ='Referencias de Custos'!$D$30 -> 35 | E65: =C65*D65 -> 70 | F65: 1x Onboarding (35.00) + 1x Offboarding (35.00)
B66: Subtotal Bruto (Custo Base) | E66: =SUM(E57:E65) -> 2999.0823
B67: Margem de Lucro BPlen (20%) | E67: =E66*'Custo de Serviços'!$D$1 -> 599.81647
B68: Subtotal + Margem | E68: =E66+E67 -> 3598.8988
B69: Taxa Checkout Cartão (5%) | E69: =E68*'Custo de Serviços'!$D$39 -> 179.94494
B70: Impostos sobre Venda (8%) | E70: =(E68+E69)*'Custo de Serviços'!$D$40 -> 302.3075
B71: Total Consolidado (Cartão) | E71: =SUM(E68:E70) -> 4081.1512
B72: Taxa Checkout PIX (1%) | E72: =E68*'Custo de Serviços'!$D$46 -> 35.988988
B73: Impostos sobre Venda PIX (8%) | E73: =(E68+E72)*'Custo de Serviços'!$D$47 -> 290.79102
B74: Parcelamento Máximo | C74: 10 | D74: - | E74: -
B75: Total Consolidado (PIX) | E75: =SUM(E68,E72:E73) -> 3925.6788
C77: 10
B78: Pacote LIDER
B79: Item de Custo | C79: Unidade | D79: Custo Unitário | E79: Custo Consolidado | F79: Racional / Origem
B80: Custos Administrativos - franquia | C80: 1 | D80: ='Referencias de Custos'!$D$34 -> 80 | E80: =C80*D80 -> 80 | F80: Cobrado apenas uma vez por cliente (DEDUPLICADO)
B81: BPlen HUB - franquia | C81: 1 | D81: ='Referencias de Custos'!$D$32 -> 29.08233 | E81: =C81*D81 -> 29.08233 | F81: Cobrado apenas uma vez por cliente (DEDUPLICADO)
B82: Posicionamento de Carreira e-book - franquia | C82: 1 | D82: ='Referencias de Custos'!D31 -> 50 | E82: =C82*D82 -> 50 | F82: Material pedagógico para condução de orientação educacional sobre Posicionamento de Carreira.
B83: Área Membro | C83: 1 | D83: ='Referencias de Custos'!$D$5 -> 15 | E83: =C83*D83 -> 15 | F83: Acesso unificado à Área do Membro (DEDUPLICADO)
B84: Área Membro | GDC Dashboard | C84: 1 | D84: ='Referencias de Custos'!$D$6 -> 15 | E84: =C84*D84 -> 15 | F84: Acesso unificado à Área do Membro GDC
B85: GDC e-book - franquia | C85: 1 | D85: ='Referencias de Custos'!$D$29 -> 200 | E85: =C85*D85 -> 200 | F85: Franquia do material didático pedagógico GDC
B86: Relatório DISC | C86: 1 | D86: ='Referencias de Custos'!$D$13 -> 160 | E86: =C86*D86 -> 160 | F86: Relatório com resultados da avaliação DISC
B87: Relatório de Análise Comportamental | C87: 1 | D87: ='Referencias de Custos'!D14 -> 160 | E87: =C87*D87 -> 160 | F87: Relatório da análise e insights do analista referente aos assessments comportamentais cruzados com contexto situacionais do cliente.
B88: Relatório PDI | C88: 1 | D88: ='Custo de Serviços'!$E$91 -> 160 | E88: =C88*D88 -> 160 | F88: Relatório do Plano de Desenvolvimento Individual (PDI)
B89: Honorário (Sessões) | C89: =90+120+180+1380 -> 1770 | D89: ='Referencias de Custos'!$D$2 -> 5.8333333 | E89: =C89*D89 -> 10325 | F89: Sessions (PC, AC, Plano, GDC) (Total: 1770 minutos / 29.5 horas)
B90: Honorário - Franquia (Onboarding/Offboarding) | C90: 2 | D90: ='Referencias de Custos'!$D$30 -> 35 | E90: =C90*D90 -> 70 | F90: 1x Onboarding (35.00) + 1x Offboarding (35.00)
B91: Subtotal Bruto (Custo Base) | E91: =SUM(E80:E90) -> 11264.082
B92: Margem de Lucro BPlen (20%) | E92: =E91*'Custo de Serviços'!$D$1 -> 2252.8165
B93: Subtotal + Margem | E93: =E91+E92 -> 13516.899
B94: Taxa Checkout Cartão (5%) | E94: =E93*'Custo de Serviços'!$D$39 -> 675.84494
B95: Impostos sobre Venda (8%) | E95: =(E93+E94)*'Custo de Serviços'!$D$40 -> 1135.4195
B96: Total Consolidado (Cartão) | E96: =SUM(E93:E95) -> 15328.163
B97: Taxa Checkout PIX (1%) | E97: =E93*'Custo de Serviços'!$D$46 -> 135.16899
B98: Impostos sobre Venda PIX (8%) | E98: =(E93+E97)*'Custo de Serviços'!$D$47 -> 1092.1654
B99: Parcelamento Máximo | C99: 12 | D99: - | E99: -
B100: Total Consolidado (PIX) | E100: =SUM(E93,E97:E98) -> 14744.233
B102: Pacote EMBAIXADOR BPLEN
B103: Item de Custo | C103: 12 | D103: Custo Unitário | E103: Custo Consolidado | F103: Racional / Origem
B104: Custos Administrativos - franquia | C104: 1 | D104: ='Referencias de Custos'!$D$34 -> 80 | E104: =C104*D104 -> 80 | F104: Cobrado apenas uma vez por cliente (DEDUPLICADO)
B105: BPlen HUB - franquia | C105: 1 | D105: ='Referencias de Custos'!$D$32 -> 29.08233 | E105: =C105*D105 -> 29.08233 | F105: Cobrado apenas uma vez por cliente (DEDUPLICADO)
B106: Posicionamento de Carreira e-book - franquia | C106: 1 | D106: ='Referencias de Custos'!D31 -> 50 | E106: =C106*D106 -> 50 | F106: Material pedagógico para condução de orientação educacional sobre Posicionamento de Carreira.
B107: Área Membro | C107: 1 | D107: ='Referencias de Custos'!$D$5 -> 15 | E107: =C107*D107 -> 15 | F107: Acesso unificado à Área do Membro (DEDUPLICADO)
B108: Área Membro | GDC Dashboard | C108: 1 | D108: ='Referencias de Custos'!$D$6 -> 15 | E108: =C108*D108 -> 15 | F108: Acesso unificado à Área do Membro GDC
B109: Área Membro | MentoCoach Dashboard | C109: 1 | D109: ='Custo de Serviços'!E153 -> 250 | E109: =C109*D109 -> 250 | F109: Acesso unificado à Área MentoCoach
...

Sheet Metas
D2: BPlen HUB
D3: Plano Estratégico de Metas Comerciais & Amortização de Custos (24 Meses)
B6: 1. Resumo das Franquias de Custos Fixos (Investimentos a Amortizar)
B7: Franquia / Custo | C7: Descrição do Custo Relacionado | D7: Custo Total Investido | E7: Meta de Clientes para Diluição | F7: Valor Diluído Aplicado por Cliente
B8: BPlen HUB (CapEx Portal) | C8: Desenvolvimento do ecossistema e área logada do portal BPlen HUB | D8: ='BPlen HUB Custos'!$C$25 -> 29082.33 | E8: 1000 | F8: =D8/E8 -> 29.08233
B9: MentoCoach (Metodologia) | C9: Metodologia, licença e assessments Coaching IBC | D9: ='MentoCoach Custos'!$B$5 -> 6000 | E9: 20 | F9: =D9/E9 -> 300
B10: GDC e-book (Pedagógico) | C10: Material didático pedagógico de Gestão e Desenvolvimento de Carreira | D10: ='Referencias de Custos'!$C$25 -> 5000 | E10: 25 | F10: =D10/E10 -> 200
B11: Posicionamento de Carreira e-book | C11: Material didático pedagógico de Posicionamento de Carreira | D11: ='Referencias de Custos'!D26 -> 5000 | E11: 25 | F11: =D11/E11 -> 200
B12: Custos Administrativos | C12: Despesas operacionais e administrativas gerais (Anual) | D12: ='Custos gerais'!$C$4 -> 24000 | E12: 300 | F12: =D12/E12 -> 80
B13: TOTAL DE INVESTIMENTOS EM FRANQUIAS | D13: =SUM(D8:D12) -> 69082.33
B16: 2. Cronograma Sugerido de Metas e Amortização em Fases
B17: Fase Estratégica | C17: Período (Meses) | D17: Meta Acumulada de Clientes | E17: Ritmo de Vendas (Clientes/Mês) | F17: Custos Fixos Amortizados no Período | G17: Foco Comercial / Pacotes Sugeridos
B18: Fase 1: Curto Prazo (Startup) | C18: 1 a 3 | D18: 25 | E18: =E18/3 | F18: Amortização de MentoCoach (20) & GDC e-book (25) | G18: Foco em Pacotes Pleno e Senior (Validação comercial)
B19: Fase 2: Médio Prazo (Breakeven) | C19: 4 a 12 | D19: 300 | E19: =(E19-E18)/9 | F19: Amortização do Custo Administrativo Anual (R$ 24k / 300) | G19: Foco em Pacotes Senior, Lider e Introdução de Recorrência
B20: Fase 3: Longo Prazo (Expansão) | C20: 13 a 24 | D20: 1000 | E20: =(E20-E19)/12 | F20: Amortização do Desenvolvimento BPlen HUB (R$ 29k / 1000) | G20: Foco em Lider, Embaixador BPlen e Franquias para Parceiros
B21: TOTAL GERAL DO PLANO (2 ANOS) | C21: 24 Meses | D21: =E20 | E21: =E21/24 | F21: 100% de Amortização Concluída!
B24: 3. Simulador de Viabilidade e Projeção de Faturamento Bruto (Meta 1000 Clientes)
B25: Pacote de Serviço | C25: Preço Sugerido (Venda PIX) | D25: Mix de Vendas Estimado (%) | E25: Volume de Vendas (Fase 1-3) | F25: Projeção de Faturamento Bruto
B26: Junior | C26: ='Pacotes de Serviço'!$G$8 -> 895.44 | D26: 0.1 | E26: =D26*$E$31 | F26: =C26*E26
B27: Pleno | C27: ='Pacotes de Serviço'!$G$9 -> 2341.84 | D27: 0.3 | E27: =D27*$E$31 | F27: =C27*E27
B28: Senior | C28: ='Pacotes de Serviço'!$G$10 -> 3925.68 | D28: 0.35 | E28: =D28*$E$31 | F28: =C28*E28
B29: Lider | C29: ='Pacotes de Serviço'!$G$11 -> 14744.23 | D29: 0.2 | E29: =D29*$E$31 | F29: =C29*E29
B30: Embaixador BPlen | C30: ='Pacotes de Serviço'!$G$12 -> 22859.79 | D30: 0.05 | E30: =D30*$E$31 | F30: =C30*E30
B31: TOTAL PROJETADO / TARGET GERAL | D31: =SUM(D26:D30) -> 1 | E31: =E21 | F31: =SUM(F26:F30)

Sheet Jornada
A1: isStepJourney | B1: ServiceCode | C1: Order | D1: ServiceName
A2: clientes_b2c | B2: BPL-000 | C2: 2 | D2: Onboarding
A3: clientes_b2c | B3: BPL-001 | C3: 1 | D3: Posicionamento de Carreira
A4: clientes_b2c | B4: BPL-002 | C4: 3 | D4: Análise Comportamental
A5: clientes_b2c | B5: BPL-003 | C5: 4 | D5: Plano de Carreira
A6: clientes_b2c | B6: BPL-004 | C6: 5 | D6: Gestão e Desenvolvimento de Carreira
A7: clientes_b2c | B7: BPL-005 | C7: 6 | D7: MentoCoach
A8: clientes_b2c | B8: BPL-006 | C8: 7 | D8: Offboarding
A9: parceiros | B9: BPP-001 | C9: 1 | D9: Jornada de Parceiro
A10: parceiros | B10: BPP-002 | C10: 2 | D10: Configuração de Networking
A11: parceiros | B11: BPP-003 | C11: 3 | D11: Ativação de Parceria

Sheet Checkpoints
A1: ServiceCode | C1: CheckpointId | D1: Order | E1: Title | F1: Type | G1: ReferenceId | H1: Description
A2: BPL-000 | B2: Onboarding | C2: introducao | D2: 1 | E2: Introdução | F2: content | G2: welcome_video_01 | H2: Conheça o BPlen HUB
A3: BPL-000 | B3: Onboarding | C3: check_in_survey | D3: 2 | E3: Check-in | F3: survey | G3: check_in | H3: Pre-mapa do estado atual
A4: BPL-000 | B4: Onboarding | C4: sessao_onboarding | D4: 3 | E4: Sessão de Onboarding | F4: meeting | G4: onboarding | H4: Boas-vindas e alinhamento de expectativas
A5: BPL-001 | B5: Posicionamento de Carreira | C5: realizar_desmistificando_candidaturas | D5: 1 | E5: Oportunidades e Mercado Oculto | F5: survey | G5: desmistificando_candidaturas | H5: A realidade do mercado de trabalho
A6: BPL-001 | B6: Posicionamento de Carreira | C6: realizar_pdi_fase1 | D6: 2.1 | E6: Elaboração de PDI | F6: survey | G6: survey_pdi_fase1 | H6: Definição de objetivos de carreira profissional
A7: BPL-001 | B7: Posicionamento de Carreira | C7: realizar_pdi_fase2 | D7: 2.2 | E7: Elaboração de PDI | F7: survey | G7: survey_pdi_fase2 | H7: Analise de Potencial e Riscos
A8: BPL-001 | B8: Posicionamento de Carreira | C8: realizar_pdi_fase3 | D8: 2.3 | E8: Elaboração de PDI | F8: survey | G8: survey_pdi_fase3 | H8: Definição de metas e ciclos
A9: BPL-001 | B9: Posicionamento de Carreira | C9: realizar_pdi_fase4 | D9: 2.4 | E9: Elaboração de PDI | F9: survey | G9: survey_pdi_fase4 | H9: Consolidação do PDI
A10: BPL-001 | B10: Posicionamento de Carreira | C10: realizar_master_cv | D10: 3.1 | E10: CV e Perfil Profissional | F10: survey | G10: master_cv | H10: Central de do histórico profissional
A11: BPL-001 | B11: Posicionamento de Carreira | C11: realizar_cv_focado | D11: 3.2 | E11: CV e Perfil Profissional | F11: survey | G11: cv_focado | H11: Adaptação do CV com foco no objetivo pretendido
A12: BPL-001 | B12: Posicionamento de Carreira | C12: realizar_perfil_profissional_publico | D12: 3.3 | E12: CV e Perfil Profissional | F12: survey | G12: perfil_profissional_publico | H12: Aplicação do CV nos perfis profissionais online
A13: BPL-001 | B13: Posicionamento de Carreira | C13: realizar_preparacao_entrevistas_networking | D13: 4 | E13: Entrevistas e Networking | F13: survey | G13: preparacao_entrevistas_networking | H13: Preparação de apresentação e pitch em entrevistas e reuniões de networking
A14: BPL-001 | B14: Posicionamento de Carreira | C14: realizar_pre_analise_comportamental | D14: 5.1 | E14: Consultoria de Feedback | F14: survey | G14: pre_analise_comportamental | H14: Análise Comportamental Básica
A15: BPL-001 | B15: Posicionamento de Carreira | C15: agendar-feedback-posicionamento-profissional | D15: 5.2 | E15: Consultoria de Feedback | F15: meeting | G15: feedback-posicionamento-profissional | H15: Sessão de feedback do Posicionamento Profissional
A16: BPL-002 | B16: Análise Comportamental | C16: realizar-disc | D16: 1 | E16: DISC | F16: survey | G16: disc | H16: Avaliação de Perfil Comportamental
A17: BPL-002 | B17: Análise Comportamental | C17: realizar_preferencias_reconhecimento | D17: 2 | E17: Preferências de Reconhecimento | F17: survey | G17: preferencias_reconhecimento | H17: Mapa de preferências de reconhecimento interpessoal
A18: BPL-002 | B18: Análise Comportamental | C18: realizar_preferencias_aprendizado | D18: 3 | E18: Preferências de Aprendizado | F18: survey | G18: preferencias_aprendizado | H18: Mapa de preferências de formas e habitos de aprendizado
A19: BPL-002 | B19: Análise Comportamental | C19: realizar_gestao_tempo | D19: 4 | E19: Mapa de Gestão de Tempo | F19: survey | G19: gestao_tempo | H19: Mapa de habitos de priorização de tarefas e tempo
A20: BPL-002 | B20: Análise Comportamental | C20: agendar-devolutiva | D20: 5 | E20: Devolutiva de Análise | F20: meeting | G20: devolutiva-analise-comportamental | H20: Sessão individual de Devolutiva Comportamental
A21: BPL-003 | B21: Plano de Carreira | C21: realizar_survey_plano_acordos | D21: 1 | E21: Avisos e Acordos | F21: survey | G21: survey_plano_acordos | H21: Avisos e cordos do processo
A22: BPL-003 | B22: Plano de Carreira | C22: realizar_survey_plano_fase1 | D22: 2 | E22: Definição de Objetivos | F22: survey | G22: survey_plano_fase1 | H22: Definição de objetivos de carreira profissional
A23: BPL-003 | B23: Plano de Carreira | C23: realizar_survey_plano_fase2 | D23: 3 | E23: Seleção de Recursos | F23: survey | G23: survey_plano_fase2 | H23: Seleção de recursos para utilização durante a jornada
A24: BPL-003 | B24: Plano de Carreira | C24: realizar_survey_plano_fase3 | D24: 4 | E24: Plano de Ação | F24: survey | G24: survey_plano_fase3 | H24: Plano de ação para manter foco e ritmo
A25: BPL-003 | B25: Plano de Carreira | C25: realizar_survey_plano_fase4 | D25: 5 | E25: Consolidação do Plano | F25: survey | G25: survey_plano_fase4 | H25: Consolidação do plano para ativação assertiva
A26: BPL-003 | B26: Plano de Carreira | C26: agendar-devolutiva-plano | D26: 6.1 | E26: Devolutiva do Plano | F26: survey | G26: survey_agendamento_devolutiva | H26: Organização de materiais para sessão de devolutiva do plano
A27: BPL-003 | B27: Plano de Carreira | C27: agendar-devolutiva-plano | D27: 6.2 | E27: Devolutiva do Plano | F27: meeting | G27: devolutiva-plano-carreira | H27: Sessão individual de devolutiva do plano
A28: BPL-004 | B28: Gestão e Desenvolvimento de Carreira | C28: agendar-sessao | D28: 1 | E28: Autoconhecimento e Aprendizagem | F28: meeting | G28: orientacao-em-grupo | H28: Autoconhecimento e Aprendizagem
A29: BPL-004 | B29: Gestão e Desenvolvimento de Carreira | C29: agendar-sessao | D29: 2 | E29: Gestão Comportamental e Emocional | F29: meeting | G29: orientacao-em-grupo | H29: Gestão Comportamental e Emocional
A30: BPL-004 | B30: Gestão e Desenvolvimento de Carreira | C30: agendar-sessao | D30: 3 | E30: Técnicas de Posicionamento | F30: meeting | G30: orientacao-em-grupo | H30: Técnicas de Posicionamento
A31: BPL-004 | B31: Gestão e Desenvolvimento de Carreira | C31: agendar-sessao | D31: 4 | E31: Gestão de Tempo e Tarefas | F31: meeting | G31: orientacao-em-grupo | H31: Gestão de Tempo e Tarefas
A32: BPL-004 | B32: Gestão e Desenvolvimento de Carreira | C32: agendar-sessao | D32: 5 | E32: Comunicação e Relacionamento Interpessoal | F32: meeting | G32: orientacao-em-grupo | H32: Comunicação e Relacionamento Interpessoal
A33: BPL-004 | B33: Gestão e Desenvolvimento de Carreira | C33: agendar-sessao | D33: 6 | E33: Técnicas de Negociação | F33: meeting | G33: orientacao-em-grupo | H33: Técnicas de Negociação
A34: BPL-004 | B34: Gestão e Desenvolvimento de Carreira | C34: agendar-sessao | D34: 7 | E34: Networking e Geração de Valor | F34: meeting | G34: orientacao-em-grupo | H34: Networking e Geração de Valor
A35: BPL-004 | B35: Gestão e Desenvolvimento de Carreira | C35: agendar-sessao | D35: 8 | E35: Finanças para Carreira Profissional | F35: meeting | G35: orientacao-em-grupo | H35: Finanças para Carreira Profissional
A36: BPL-004 | B36: Gestão e Desenvolvimento de Carreira | C36: agendar-sessao | D36: 9 | E36: Liderança e Autoliderança | F36: meeting | G36: orientacao-em-grupo | H36: Liderança e Autoliderança
A37: BPL-004 | B37: Gestão e Desenvolvimento de Carreira | C37: agendar-sessao | D37: 10 | E37: Práticas de Melhoria Contínua | F37: meeting | G37: orientacao-em-grupo | H37: Práticas de Melhoria Contínua
A38: BPL-005 | B38: MentoCoach | C38: realizar-disc | D38: 1.1 | E38: Análise Comportamental | F38: survey | G38: disc | H38: Avaliação de Perfil Comportamental (DISC)
A39: BPL-005 | B39: MentoCoach | C39: realizar_preferencias_reconhecimento | D39: 1.2 | E39: Análise Comportamental | F39: survey | G39: preferencias_reconhecimento | H39: Mapa de preferências de reconhecimento interpessoal
A40: BPL-005 | B40: MentoCoach | C40: realizar_preferencias_aprendizado | D40: 1.3 | E40: Análise Comportamental | F40: survey | G40: preferencias_aprendizado | H40: Mapa de preferências de formas e habitos de aprendizado
A41: BPL-005 | B41: MentoCoach | C41: realizar_gestao_tempo | D41: 1.4 | E41: Análise Comportamental | F41: survey | G41: gestao_tempo | H41: Mapa de habitos de priorização de tarefas e tempo
A42: BPL-005 | B42: MentoCoach | C42: agendar-devolutiva | D42: 1.5 | E42: Análise Comportamental | F42: meeting | G42: devolutiva-analise-comportamental | H42: Sessão individual de Devolutiva Comportamental
A43: BPL-005 | B43: MentoCoach | C43: agendar-sessao-mentocoach | D43: 2 | E43: 1ª Sessão de MentoCoach | F43: meeting | G43: sessao-mentocoach | H43: 1ª Sessão de MentoCoach
A44: BPL-005 | B44: MentoCoach | C44: agendar-sessao-mentocoach | D44: 3 | E44: 2ª Sessão de MentoCoach | F44: meeting | G44: sessao-mentocoach | H44: 2ª Sessão de MentoCoach
A45: BPL-005 | B45: MentoCoach | C45: agendar-sessao-mentocoach | D45: 4 | E45: 3ª Sessão de MentoCoach | F45: meeting | G45: sessao-mentocoach | H45: 3ª Sessão de MentoCoach
A46: BPL-005 | B46: MentoCoach | C46: agendar-sessao-mentocoach | D46: 5 | E46: 4ª Sessão de MentoCoach | F46: meeting | G46: sessao-mentocoach | H46: 4ª Sessão de MentoCoach
A47: BPL-005 | B47: MentoCoach | C47: agendar-sessao-mentocoach | D47: 6 | E47: 5ª Sessão de MentoCoach | F47: meeting | G47: sessao-mentocoach | H47: 5ª Sessão de MentoCoach
A48: BPL-005 | B48: MentoCoach | C48: agendar-sessao-mentocoach | D48: 7 | E48: 6ª Sessão de MentoCoach | F48: meeting | G48: sessao-mentocoach | H48: 6ª Sessão de MentoCoach
A49: BPL-005 | B49: MentoCoach | C49: agendar-sessao-mentocoach | D49: 8 | E49: 7ª Sessão de MentoCoach | F49: meeting | G49: sessao-mentocoach | H49: 7ª Sessão de MentoCoach
A50: BPL-005 | B50: MentoCoach | C50: agendar-sessao-mentocoach | D50: 9 | E50: 8ª Sessão de MentoCoach | F50: meeting | G50: sessao-mentocoach | H50: 8ª Sessão de MentoCoach
A51: BPL-005 | B51: MentoCoach | C51: agendar-sessao-mentocoach | D51: 10 | E51: 9ª Sessão de MentoCoach | F51: meeting | G51: sessao-mentocoach | H51: 9ª Sessão de MentoCoach
A52: BPL-005 | B52: MentoCoach | C52: agendar-sessao-mentocoach | D52: 11 | E52: 10ª Sessão de MentoCoach | F52: meeting | G52: sessao-mentocoach | H52: 10ª Sessão de MentoCoach
A53: BPL-006 | B53: Offboarding | C53: offboarding-survey | D53: 1 | E53: Avaliação Final | F53: survey | G53: offboarding_survey | H53: Avalição de encerramento e consolidação de resultados.
A54: BPL-006 | B54: Offboarding | C54: sessao_onboarding | D54: 2 | E54: Sessão de Offboarding | F54: meeting | G54: offboarding | H54: Encerramento e alinhamento de próximos passos
A55: BPP-001 | B55: Onboarding de Parceiro | C55: sessao_onboarding_de_parceiro | D55: 1 | E55: Introdução | F55: tour | G55: tour_guided_parceiro | H55: Conheça a BPlen HUB para Parceiros
A56: BPP-001 | B56: Onboarding de Parceiro | C56: realizar_partner_check_in | D56: 2.1 | E56: Check-in | F56: survey | G56: partner_check_in | H56: Alinhamento de Expectativas
A57: BPP-001 | B57: Onboarding de Parceiro | C57: realizar_partner_dados_cadastrais | D57: 2.2 | E57: Check-in | F57: form | G57: partner_dados_cadastrais | H57: Configuração de Dados Cadastrais
A58: BPP-001 | B58: Onboarding de Parceiro | C58: assinar_formalizacao-parceria | D58: 3 | E58: Formalização | F58: contract | G58: formalizacao-parceria | H58: Validação e assinatura de formalização de parceria
A59: BPP-001 | B59: Onboarding de Parceiro | C59: sessao_onboarding_de_parceiro | D59: 4 | E59: Sessão de Onboarding | F59: meeting | G59: onboarding_de_parceiro | H59: Boas-vindas e alinhamento de expectativas
A60: BPP-002 | B60: Configuração de Networking | C60: configurar_/hub/profile_settings | D60: 1 | E60: Configurar Networking | F60: action | G60: /hub/profile_settings | H60: Configuração do Perfil para a Página de Networking
A61: BPP-003 | B61: Ativação de Parceria | C61: acompanhar/hub/partners | D61: 1 | E61: Gestão Contínua de Parceria | F61: action | G61: /hub/partners | H61: Ativação de oficial da jornada de parceiro e acompanhamento do progresso

Sheet Atributos
A1: serviceCode | B1: serviceName | C1: escopo | D1: concedeSelo | E1: preReqModo | F1: preReqEtapas | G1: libera | H1: sku | I1: nbs | J1: naturezaOperacao | K1: descricaoFiscal
A2: BPL-001 | B2: Posicionamento de Carreira | C2: public | D2: FALSE | E2: apos_contratadas
A3: BPL-000 | B3: Onboarding | C3: member | D3: FALSE | E3: nenhum
A4: BPL-002 | B4: Análise Comportamental | C4: member | D4: TRUE | E4: todos | F4: BPL-000
A5: BPL-003 | B5: Plano de Carreira | C5: member | D5: TRUE | E5: todos | F5: BPL-000,BPL-002
A6: BPL-004 | B6: Gestão e Desenv. de Carreira | C6: member | D6: TRUE | E6: todos | F6: BPL-000,BPL-003
A7: BPL-005 | B7: MentoCoach | C7: member | D7: TRUE | E7: apos_contratadas
A8: BPL-006 | B8: Offboarding | C8: member | D8: FALSE | E8: qualquer | F8: BPL-004,BPL-005
A9: BPL-PAC-JR | B9: Pacote Junior | C9: public | D9: FALSE | E9: nenhum | G9: BPL-001
A10: BPL-PAC-PL | B10: Pacote Pleno | C10: member | D10: TRUE | E10: nenhum | G10: BPL-000,BPL-001,BPL-002
A11: BPL-PAC-SR | B11: Pacote Senior | C11: member | D11: TRUE | E11: nenhum | G11: BPL-000,BPL-001,BPL-002,BPL-003
A12: BPL-PAC-LD | B12: Pacote Líder | C12: member | D12: TRUE | E12: nenhum | G12: BPL-000,BPL-001,BPL-002,BPL-003,BPL-004
A13: BPL-PAC-EB | B13: Pacote Embaixador | C13: member | D13: TRUE | E13: nenhum | G13: BPL-000,BPL-001,BPL-002,BPL-003,BPL-004,BPL-005
